pytest_briefcase.py
pytest_briefcase-0.1.1.dist-info/LICENSE
pytest_briefcase-0.1.1.dist-info/METADATA
pytest_briefcase-0.1.1.dist-info/WHEEL
pytest_briefcase-0.1.1.dist-info/entry_points.txt
pytest_briefcase-0.1.1.dist-info/top_level.txt
pytest_briefcase-0.1.1.dist-info/RECORD
